woahlib/__init__.py
woahlib/base64.py
woahlib/listlib.py
woahlib/matrixing.py
woahlib/p2p.py
woahlib/progress.py
WOAHLIB-1.3.4.dist-info/METADATA
WOAHLIB-1.3.4.dist-info/WHEEL
WOAHLIB-1.3.4.dist-info/licence.txt
WOAHLIB-1.3.4.dist-info/top_level.txt
WOAHLIB-1.3.4.dist-info/RECORD
