Metadata-Version: 2.1
Name: WOAHLIB
Version: 1.3.4
Summary: Woah!
Home-page: https://pypi.org/project/WOAHLIB/
Author: Woah
Author-email: davidbeumers@gmail.com
License: MIT
License-File: licence.txt
